{
  "id": "",
  "name": "",
  "font_family": "iconfont",
  "css_prefix_text": "icon-",
  "description": "",
  "glyphs": [
    {
      "icon_id": "569811",
      "name": "全球",
      "font_class": "quanqiu",
      "unicode": "e6c0",
      "unicode_decimal": 59072
    },
    {
      "icon_id": "1020323",
      "name": "右箭头",
      "font_class": "youjiantou",
      "unicode": "e658",
      "unicode_decimal": 58968
    },
    {
      "icon_id": "1110411",
      "name": "下箭头",
      "font_class": "jiantou9",
      "unicode": "e60b",
      "unicode_decimal": 58891
    },
    {
      "icon_id": "1629893",
      "name": "闹钟",
      "font_class": "icon-test",
      "unicode": "e614",
      "unicode_decimal": 58900
    },
    {
      "icon_id": "2167053",
      "name": "放映机",
      "font_class": "fangyingji",
      "unicode": "e6bd",
      "unicode_decimal": 59069
    },
    {
      "icon_id": "2495837",
      "name": "百度",
      "font_class": "baidu",
      "unicode": "e7aa",
      "unicode_decimal": 59306
    },
    {
      "icon_id": "2736530",
      "name": "电脑",
      "font_class": "diannao",
      "unicode": "e64f",
      "unicode_decimal": 58959
    },
    {
      "icon_id": "2762477",
      "name": "语音",
      "font_class": "yuyin",
      "unicode": "e60d",
      "unicode_decimal": 58893
    },
    {
      "icon_id": "3550768",
      "name": "左箭头",
      "font_class": "ico_leftarrow",
      "unicode": "e670",
      "unicode_decimal": 58992
    },
    {
      "icon_id": "4970577",
      "name": "20°夏令营众筹",
      "font_class": "xialingyingzhongchou",
      "unicode": "e65e",
      "unicode_decimal": 58974
    },
    {
      "icon_id": "5032484",
      "name": "蚂蚁云金融-移动端",
      "font_class": "mayiyunjinrong-yidongduan",
      "unicode": "e501",
      "unicode_decimal": 58625
    },
    {
      "icon_id": "5107317",
      "name": "手机",
      "font_class": "shouji",
      "unicode": "e61b",
      "unicode_decimal": 58907
    },
    {
      "icon_id": "6133349",
      "name": "银联支付",
      "font_class": "yinlianzhifu",
      "unicode": "e603",
      "unicode_decimal": 58883
    },
    {
      "icon_id": "7445760",
      "name": "CFCA@1x",
      "font_class": "CFCAx",
      "unicode": "e606",
      "unicode_decimal": 58886
    },
    {
      "icon_id": "7530730",
      "name": "中国人保",
      "font_class": "zhongguorenbao",
      "unicode": "e60e",
      "unicode_decimal": 58894
    },
    {
      "icon_id": "8943715",
      "name": "产品_用户支付",
      "font_class": "chanpin_yonghuzhifu",
      "unicode": "e604",
      "unicode_decimal": 58884
    },
    {
      "icon_id": "9222237",
      "name": "大庆产业金融服务平台logo",
      "font_class": "daqingchanyejinrongfuwupingtailogo",
      "unicode": "e637",
      "unicode_decimal": 58935
    },
    {
      "icon_id": "9509973",
      "name": "拨打电话_01",
      "font_class": "bodadianhua_",
      "unicode": "e612",
      "unicode_decimal": 58898
    },
    {
      "icon_id": "9730707",
      "name": "新闻",
      "font_class": "xinwen",
      "unicode": "e502",
      "unicode_decimal": 58626
    },
    {
      "icon_id": "10201414",
      "name": "人寿",
      "font_class": "renshouw",
      "unicode": "e66f",
      "unicode_decimal": 58991
    },
    {
      "icon_id": "10734267",
      "name": "360CLOUD",
      "font_class": "CLOUD",
      "unicode": "e697",
      "unicode_decimal": 59031
    }
  ]
}
